doccano_mini/__init__.py
doccano_mini/cli.py
doccano_mini/components.py
doccano_mini/docs/README.md
doccano_mini/docs/usage.md
doccano_mini/examples/named_entity_recognition.json
doccano_mini/examples/paraphrase.json
doccano_mini/examples/question_answering.json
doccano_mini/examples/summarization.json
doccano_mini/examples/task_free.json
doccano_mini/examples/text_classification.json
doccano_mini/home.py
doccano_mini/layout.py
doccano_mini/models/entity.py
doccano_mini/models/stepper.py
doccano_mini/pages/01_Text_Classification.py
doccano_mini/pages/02_Question_Answering.py
doccano_mini/pages/03_Summarization.py
doccano_mini/pages/04_Paraphrase.py
doccano_mini/pages/05_Named_Entity_Recognition.py
doccano_mini/pages/06_(Beta)_Evaluation.py
doccano_mini/pages/09_Task_Free.py
doccano_mini/prompts.py
doccano_mini/storages/entity.py
doccano_mini/storages/session_storage.py
doccano_mini/storages/stepper.py
doccano_mini/utils.py
doccano_mini-0.0.10.dist-info/LICENSE
doccano_mini-0.0.10.dist-info/METADATA
doccano_mini-0.0.10.dist-info/WHEEL
doccano_mini-0.0.10.dist-info/entry_points.txt
doccano_mini-0.0.10.dist-info/RECORD
