Metadata-Version: 2.1
Name: doccano-mini
Version: 0.0.10
Summary: Annotation meets Large Language Models.
Home-page: https://github.com/doccano/doccano-mini
License: MIT
Author: Hironsan
Author-email: hiroki.nakayama.py@gmail.com
Requires-Python: >=3.8, !=2.7.*, !=3.0.*, !=3.1.*, !=3.2.*, !=3.3.*, !=3.4.*, !=3.5.*, !=3.6.*, !=3.7.*
Classifier: License :: OSI Approved :: MIT License
Classifier: Programming Language :: Python
Classifier: Programming Language :: Python :: 3
Classifier: Programming Language :: Python :: 3.9
Classifier: Programming Language :: Python :: 3.10
Classifier: Programming Language :: Python :: 3.11
Classifier: Programming Language :: Python :: 3.10
Classifier: Programming Language :: Python :: 3.8
Classifier: Programming Language :: Python :: 3.9
Requires-Dist: datasets (>=2.11.0,<3.0.0)
Requires-Dist: langchain (>=0.0.113,<0.0.114)
Requires-Dist: more-itertools (>=9.1.0,<10.0.0)
Requires-Dist: openai (>=0.27.2,<0.28.0)
Requires-Dist: scikit-learn (>=1.2.2,<2.0.0)
Requires-Dist: st-ner-annotate (>=0.1.0,<0.2.0)
Requires-Dist: streamlit (>=1.20.0,<2.0.0)
Project-URL: Repository, https://github.com/doccano/doccano-mini
